{"assets":[{"id":"6","layers":[{"ind":5,"ty":4,"ks":{},"ip":0,"op":506.2,"st":0,"shapes":[{"ty":"rc","p":{"a":0,"k":[90,120.5]},"r":{"a":0,"k":0},"s":{"a":0,"k":[180,241]}},{"ty":"fl","c":{"a":0,"k":[0,0,0,0]},"o":{"a":0,"k":0}}]},{"ind":0,"ty":4,"ks":{"s":{"a":0,"k":[133.33,133.33]}},"ip":0,"op":506.2,"st":0,"shapes":[{"ty":"gr","it":[{"ty":"gr","it":[{"ty":"sh","ks":{"a":0,"k":{"c":true,"i":[[0,0],[0,0],[0,0],[0,0]],"o":[[0,0],[0,0],[0,0],[0,0]],"v":[[84.46,179.85],[52.66,180.12],[52.52,164.22],[84.32,163.95]]}}},{"ty":"sh","ks":{"a":0,"k":{"c":true,"i":[[0,0],[0,0],[0,0],[0,0]],"o":[[0,0],[0,0],[0,0],[0,0]],"v":[[68.36,156.13],[36.56,156.4],[36.43,140.5],[68.22,140.23]]}}},{"ty":"sh","ks":{"a":0,"k":{"c":true,"i":[[0,0],[0,0],[0,0],[0,0],[0,0]],"o":[[0,0],[0,0],[0,0],[0,0],[0,0]],"v":[[100.16,155.87],[84.25,156],[68.36,156.13],[68.23,140.23],[100.02,139.97]]}}},{"ty":"sh","ks":{"a":0,"k":{"c":true,"i":[[0,0],[-3.78,-6.96],[-11.27,-4.76],[0,0],[0,0],[0,0],[0,0],[0,0],[6.44,11.27],[0,0],[0.34,9.85]],"o":[[0.27,7.71],[5.73,10.55],[0,0],[0,0],[0,0],[0,0],[0,0],[-11.67,-6.05],[0,0],[-4.83,-8.9],[0,0]],"v":[[14.4,65.91],[20.53,88.21],[46.8,111.9],[44.77,116.58],[68.02,116.38],[68.16,132.29],[36.36,132.55],[36.27,122.34],[8.5,95.78],[7.8,94.53],[0,66.03]]}}},{"ty":"sh","ks":{"a":0,"k":{"c":true,"i":[[0,0],[-11.98,-9.8],[-2.99,-14.83],[7.37,-13.12],[0,0],[10.71,-5.6],[0,0],[0,0],[0,0],[0,0],[0,0],[-5.79,10.31],[2.02,11.3],[0,0],[8.94,7.63],[0,0],[12.18,0.27],[0,0]],"o":[[15.54,0.32],[11.98,9.8],[2.99,14.83],[0,0],[-6.09,10.3],[0,0],[0,0],[0,0],[0,0],[0,0],[11.29,-4.29],[5.6,-9.99],[0,0],[-2.27,-11.29],[0,0],[-9.39,-7.68],[0,0],[0,0]],"v":[[67.33,0],[109.9,15.66],[133.05,53.76],[126.29,97],[125.58,98.22],[99.88,122.5],[99.96,132.02],[68.16,132.29],[68.02,116.38],[88.65,116.21],[87.19,112.74],[113.6,90.15],[119.13,57.28],[118.92,56.19],[101.6,26.99],[100.73,26.26],[67.38,13.96],[67.26,0]]}}},{"ty":"fl","c":{"a":0,"k":[0.15,0.14,0.02,1]},"o":{"a":0,"k":100}},{"ty":"tr","o":{"a":0,"k":100}}]},{"ty":"tr","o":{"a":0,"k":100}}]}]}]},{"id":"10","layers":[{"ind":8,"ty":0,"ks":{"p":{"a":0,"k":[20,20]}},"w":180,"h":241,"ip":0,"op":506.2,"st":0,"refId":"6"},{"ind":9,"ty":4,"ks":{},"ip":0,"op":506.2,"st":0,"shapes":[{"ty":"rc","p":{"a":0,"k":[110,140.5]},"r":{"a":0,"k":0},"s":{"a":0,"k":[220,281]}},{"ty":"fl","c":{"a":0,"k":[0,0,0,0]},"o":{"a":0,"k":0}}]}]},{"id":"13","layers":[{"ind":12,"ty":0,"parent":4,"ks":{"p":{"a":0,"k":[-20,-20]}},"ef":[{"ty":29,"ef":[{"ty":0,"nm":"","v":{"a":1,"k":[{"t":0,"s":[33.33],"i":{"x":0.174,"y":0.759},"o":{"x":0.011,"y":0.227}},{"t":33.6,"s":[3.67],"i":{"x":0.722,"y":1},"o":{"x":0.35,"y":0.828}},{"t":67.2,"s":[0],"h":1},{"t":505.2,"s":[0],"h":1}]}},{"ty":7,"nm":"","v":{"a":0,"k":1}},{"ty":7,"nm":"","v":{"a":0,"k":0}}]}],"w":220,"h":281,"ip":0,"op":506.2,"st":0,"refId":"10"},{"ind":4,"ty":3,"ks":{"p":{"a":0,"k":[20,20]}},"ip":0,"op":506.2,"st":0}]},{"id":"17","layers":[{"ind":15,"ty":0,"ks":{"a":{"a":0,"k":[20,20]},"o":{"a":1,"k":[{"t":0,"s":[0],"i":{"x":0,"y":1},"o":{"x":0,"y":0}},{"t":67.2,"s":[100],"h":1},{"t":505.2,"s":[100],"h":1}]},"p":{"a":1,"k":[{"t":0,"s":[40,40],"i":{"x":[0,1],"y":[1,1]},"o":{"x":[0,0],"y":[0,0]}},{"t":67.2,"s":[130,40],"i":{"x":[1,1],"y":[1,1]},"o":{"x":[0,0],"y":[0,0]}},{"t":505.2,"s":[130,40],"h":1}]}},"w":220,"h":281,"ip":0,"op":506.2,"st":0,"refId":"13"},{"ind":16,"ty":4,"ks":{},"ip":0,"op":506.2,"st":0,"shapes":[{"ty":"rc","p":{"a":0,"k":[185,170.5]},"r":{"a":0,"k":0},"s":{"a":0,"k":[370,341]}},{"ty":"fl","c":{"a":0,"k":[0,0,0,0]},"o":{"a":0,"k":0}}]}]},{"id":"20","layers":[{"ind":19,"ty":0,"parent":3,"ks":{"p":{"a":0,"k":[-130,-40]}},"ef":[{"ty":29,"ef":[{"ty":0,"nm":"","v":{"a":1,"k":[{"t":0,"s":[0],"h":1},{"t":178.2,"s":[0],"i":{"x":0.65,"y":0.172},"o":{"x":0.278,"y":0}},{"t":202.2,"s":[3.67],"i":{"x":0.989,"y":0.773},"o":{"x":0.826,"y":0.241}},{"t":226.2,"s":[33.33],"h":1},{"t":505.2,"s":[33.33],"h":1}]}},{"ty":7,"nm":"","v":{"a":0,"k":1}},{"ty":7,"nm":"","v":{"a":0,"k":0}}]}],"w":370,"h":341,"ip":0,"op":506.2,"st":0,"refId":"17"},{"ind":3,"ty":3,"ks":{"p":{"a":0,"k":[130,40]}},"ip":0,"op":506.2,"st":0}]},{"id":"28","layers":[{"ind":27,"ty":4,"ks":{},"ip":0,"op":506.2,"st":0,"shapes":[{"ty":"rc","p":{"a":0,"k":[54.5,60]},"r":{"a":0,"k":0},"s":{"a":0,"k":[109,120]}},{"ty":"fl","c":{"a":0,"k":[0,0,0,0]},"o":{"a":0,"k":0}}]},{"ind":0,"ty":4,"ks":{"s":{"a":0,"k":[133.33,133.33]}},"ip":0,"op":506.2,"st":0,"shapes":[{"ty":"gr","it":[{"ty":"gr","it":[{"ty":"gr","it":[{"ty":"sh","ks":{"a":0,"k":{"c":true,"i":[[0,0],[0,0],[0,0],[0,0]],"o":[[0,0],[0,0],[0,0],[0,0]],"v":[[54.2,46.78],[70.18,35.62],[81.3,51.54],[65.32,62.7]]}}},{"ty":"fl","c":{"a":0,"k":[0.15,0.14,0.02,1]},"o":{"a":0,"k":100}},{"ty":"tr","o":{"a":0,"k":100}}]},{"ty":"tr","o":{"a":0,"k":100}}]},{"ty":"gr","it":[{"ty":"sh","ks":{"a":0,"k":{"c":true,"i":[[0,0],[0,0],[0,0],[0,0]],"o":[[0,0],[0,0],[0,0],[0,0]],"v":[[0,37.25],[15.98,26.09],[27.1,42.01],[11.12,53.18]]}}},{"ty":"fl","c":{"a":0,"k":[0.15,0.14,0.02,1]},"o":{"a":0,"k":100}},{"ty":"tr","o":{"a":0,"k":100}}]},{"ty":"gr","it":[{"ty":"sh","ks":{"a":0,"k":{"c":true,"i":[[0,0],[0,0],[0,0],[0,0]],"o":[[0,0],[0,0],[0,0],[0,0]],"v":[[5.55,11.16],[21.54,0],[31.96,14.93],[15.98,26.09]]}}},{"ty":"fl","c":{"a":0,"k":[0.15,0.14,0.02,1]},"o":{"a":0,"k":100}},{"ty":"tr","o":{"a":0,"k":100}}]},{"ty":"gr","it":[{"ty":"sh","ks":{"a":0,"k":{"c":true,"i":[[0,0],[0,0],[0,0],[0,0]],"o":[[0,0],[0,0],[0,0],[0,0]],"v":[[31.96,14.93],[47.94,3.77],[59.06,19.69],[43.08,30.85]]}}},{"ty":"fl","c":{"a":0,"k":[0.15,0.14,0.02,1]},"o":{"a":0,"k":100}},{"ty":"tr","o":{"a":0,"k":100}}]},{"ty":"gr","it":[{"ty":"sh","ks":{"a":0,"k":{"c":true,"i":[[0,0],[0,0],[0,0],[0,0]],"o":[[0,0],[0,0],[0,0],[0,0]],"v":[[27.1,42.01],[43.08,30.85],[54.2,46.78],[38.22,57.94]]}}},{"ty":"fl","c":{"a":0,"k":[0.15,0.14,0.02,1]},"o":{"a":0,"k":100}},{"ty":"tr","o":{"a":0,"k":100}}]},{"ty":"gr","it":[{"ty":"sh","ks":{"a":0,"k":{"c":true,"i":[[0,0],[0,0],[0,0],[0,0]],"o":[[0,0],[0,0],[0,0],[0,0]],"v":[[22.24,69.1],[38.22,57.94],[49.34,73.86],[33.36,85.02]]}}},{"ty":"fl","c":{"a":0,"k":[0.15,0.14,0.02,1]},"o":{"a":0,"k":100}},{"ty":"tr","o":{"a":0,"k":100}}]},{"ty":"gr","it":[{"ty":"sh","ks":{"a":0,"k":{"c":true,"i":[[0,0],[0,0],[0,0],[0,0]],"o":[[0,0],[0,0],[0,0],[0,0]],"v":[[49.34,73.86],[65.32,62.7],[76.45,78.63],[60.46,89.79]]}}},{"ty":"fl","c":{"a":0,"k":[0.15,0.14,0.02,1]},"o":{"a":0,"k":100}},{"ty":"tr","o":{"a":0,"k":100}}]},{"ty":"tr","o":{"a":0,"k":100}}]}]}]},{"id":"31","layers":[{"ind":30,"ty":0,"parent":26,"ks":{},"w":109,"h":120,"ip":0,"op":506.2,"st":0,"refId":"28"},{"ind":26,"ty":3,"ks":{"s":{"a":0,"k":[100.92,100.83]}},"ip":0,"op":506.2,"st":0}]},{"id":"35","layers":[{"ind":33,"ty":0,"ks":{"p":{"a":0,"k":[20,20]}},"w":110,"h":121,"ip":0,"op":506.2,"st":0,"refId":"31"},{"ind":34,"ty":4,"ks":{},"ip":0,"op":506.2,"st":0,"shapes":[{"ty":"rc","p":{"a":0,"k":[75,80.5]},"r":{"a":0,"k":0},"s":{"a":0,"k":[150,161]}},{"ty":"fl","c":{"a":0,"k":[0,0,0,0]},"o":{"a":0,"k":0}}]}]},{"id":"38","layers":[{"ind":37,"ty":0,"parent":25,"ks":{"p":{"a":0,"k":[-20,-20]}},"ef":[{"ty":29,"ef":[{"ty":0,"nm":"","v":{"a":1,"k":[{"t":0,"s":[33.33],"h":1},{"t":3,"s":[33.33],"i":{"x":0.174,"y":0.759},"o":{"x":0.011,"y":0.227}},{"t":36.6,"s":[3.67],"i":{"x":0.722,"y":1},"o":{"x":0.35,"y":0.828}},{"t":70.2,"s":[0],"h":1},{"t":505.2,"s":[0],"h":1}]}},{"ty":7,"nm":"","v":{"a":0,"k":1}},{"ty":7,"nm":"","v":{"a":0,"k":0}}]}],"w":150,"h":161,"ip":0,"op":506.2,"st":0,"refId":"35"},{"ind":25,"ty":3,"ks":{"p":{"a":0,"k":[20,20]}},"ip":0,"op":506.2,"st":0}]},{"id":"42","layers":[{"ind":40,"ty":0,"ks":{"a":{"a":0,"k":[20,20]},"o":{"a":1,"k":[{"t":0,"s":[0],"h":1},{"t":3,"s":[0],"i":{"x":0,"y":1},"o":{"x":0,"y":0}},{"t":70.2,"s":[100],"h":1},{"t":505.2,"s":[100],"h":1}]},"p":{"a":1,"k":[{"t":0,"s":[40,40],"i":{"x":[1,1],"y":[1,1]},"o":{"x":[0,0],"y":[0,0]}},{"t":3,"s":[40,40],"i":{"x":[0,1],"y":[1,1]},"o":{"x":[0,0],"y":[0,0]}},{"t":70.2,"s":[95,40],"i":{"x":[1,1],"y":[1,1]},"o":{"x":[0,0],"y":[0,0]}},{"t":505.2,"s":[95,40],"h":1}]}},"w":150,"h":161,"ip":0,"op":506.2,"st":0,"refId":"38"},{"ind":41,"ty":4,"ks":{},"ip":0,"op":506.2,"st":0,"shapes":[{"ty":"rc","p":{"a":0,"k":[132.5,110.5]},"r":{"a":0,"k":0},"s":{"a":0,"k":[265,221]}},{"ty":"fl","c":{"a":0,"k":[0,0,0,0]},"o":{"a":0,"k":0}}]}]},{"id":"45","layers":[{"ind":44,"ty":0,"parent":24,"ks":{"p":{"a":0,"k":[-95,-40]}},"ef":[{"ty":29,"ef":[{"ty":0,"nm":"","v":{"a":1,"k":[{"t":0,"s":[0],"h":1},{"t":181.2,"s":[0],"i":{"x":0.65,"y":0.172},"o":{"x":0.278,"y":0}},{"t":205.2,"s":[3.67],"i":{"x":0.989,"y":0.773},"o":{"x":0.826,"y":0.241}},{"t":229.2,"s":[33.33],"h":1},{"t":505.2,"s":[33.33],"h":1}]}},{"ty":7,"nm":"","v":{"a":0,"k":1}},{"ty":7,"nm":"","v":{"a":0,"k":0}}]}],"w":265,"h":221,"ip":0,"op":506.2,"st":0,"refId":"42"},{"ind":24,"ty":3,"ks":{"p":{"a":0,"k":[95,40]}},"ip":0,"op":506.2,"st":0}]},{"id":"54","layers":[{"ind":53,"ty":4,"parent":52,"ks":{},"ef":[{"ty":29,"ef":[{"ty":0,"nm":"","v":{"a":1,"k":[{"t":0,"s":[33.33],"h":1},{"t":322.74,"s":[33.33],"i":{"x":0.174,"y":0.759},"o":{"x":0.011,"y":0.227}},{"t":344.7,"s":[3.67],"i":{"x":0.722,"y":1},"o":{"x":0.35,"y":0.828}},{"t":366.66,"s":[0],"h":1},{"t":505.2,"s":[0],"h":1}]}},{"ty":7,"nm":"","v":{"a":0,"k":1}},{"ty":7,"nm":"","v":{"a":0,"k":0}}]}],"ip":0,"op":506.2,"st":0,"shapes":[{"ty":"gr","it":[{"ty":"rc","p":{"a":0,"k":[30,53.625]},"r":{"a":0,"k":0},"s":{"a":0,"k":[100,115]}},{"ty":"fl","c":{"a":0,"k":[0,0,0,0]},"o":{"a":0,"k":0}},{"ty":"tr","o":{"a":0,"k":100}}]},{"ty":"gr","it":[{"ty":"sh","ks":{"a":0,"k":{"c":true,"i":[[0,0],[0,0],[0,0],[0,0],[0,0],[0,0],[0,0],[0,0],[0,0]],"v":[[45,16.1],[45,31.1],[15,31.1],[15,76.1],[45,76.1],[45,91.1],[0,91.1],[0,16.1],[45,16.1]],"o":[[0,0],[0,0],[0,0],[0,0],[0,0],[0,0],[0,0],[0,0],[0,0]]}}},{"ty":"sh","ks":{"a":0,"k":{"c":true,"i":[[0,0],[0,0],[0,0],[0,0],[0,0]],"v":[[45,76.1],[45,31.1],[60,31.1],[60,76.1],[45,76.1]],"o":[[0,0],[0,0],[0,0],[0,0],[0,0]]}}},{"ty":"fl","c":{"a":0,"k":[0.153,0.137,0.024]},"o":{"a":0,"k":100}},{"ty":"tr","o":{"a":0,"k":100}}]}]},{"ind":52,"ty":3,"ks":{"p":{"a":0,"k":[20,4]}},"ip":0,"op":506.2,"st":0}]},{"id":"59","layers":[{"ind":58,"ty":4,"parent":57,"ks":{},"ef":[{"ty":29,"ef":[{"ty":0,"nm":"","v":{"a":1,"k":[{"t":0,"s":[33.33],"h":1},{"t":317.28,"s":[33.33],"i":{"x":0.174,"y":0.759},"o":{"x":0.011,"y":0.227}},{"t":339.24,"s":[3.67],"i":{"x":0.722,"y":1},"o":{"x":0.35,"y":0.828}},{"t":361.2,"s":[0],"h":1},{"t":505.2,"s":[0],"h":1}]}},{"ty":7,"nm":"","v":{"a":0,"k":1}},{"ty":7,"nm":"","v":{"a":0,"k":0}}]}],"ip":0,"op":506.2,"st":0,"shapes":[{"ty":"gr","it":[{"ty":"rc","p":{"a":0,"k":[30,53.625]},"r":{"a":0,"k":0},"s":{"a":0,"k":[100,115]}},{"ty":"fl","c":{"a":0,"k":[0,0,0,0]},"o":{"a":0,"k":0}},{"ty":"tr","o":{"a":0,"k":100}}]},{"ty":"gr","it":[{"ty":"sh","ks":{"a":0,"k":{"c":true,"i":[[0,0],[0,0],[0,0],[0,0],[0,0],[0,0],[0,0],[0,0],[0,0]],"v":[[15,61.1],[15,76.1],[0,76.1],[0,31.1],[15,31.1],[15,46.1],[60,46.1],[60,61.1],[15,61.1]],"o":[[0,0],[0,0],[0,0],[0,0],[0,0],[0,0],[0,0],[0,0],[0,0]]}}},{"ty":"sh","ks":{"a":0,"k":{"c":true,"i":[[0,0],[0,0],[0,0],[0,0],[0,0]],"v":[[15,31.1],[15,16.1],[60,16.1],[60,31.1],[15,31.1]],"o":[[0,0],[0,0],[0,0],[0,0],[0,0]]}}},{"ty":"sh","ks":{"a":0,"k":{"c":true,"i":[[0,0],[0,0],[0,0],[0,0],[0,0]],"v":[[15,91.1],[15,76.1],[60,76.1],[60,91.1],[15,91.1]],"o":[[0,0],[0,0],[0,0],[0,0],[0,0]]}}},{"ty":"fl","c":{"a":0,"k":[0.153,0.137,0.024]},"o":{"a":0,"k":100}},{"ty":"tr","o":{"a":0,"k":100}}]}]},{"ind":57,"ty":3,"ks":{"p":{"a":0,"k":[20,4]}},"ip":0,"op":506.2,"st":0}]},{"id":"64","layers":[{"ind":63,"ty":4,"parent":62,"ks":{},"ef":[{"ty":29,"ef":[{"ty":0,"nm":"","v":{"a":1,"k":[{"t":0,"s":[33.33],"h":1},{"t":311.82,"s":[33.33],"i":{"x":0.174,"y":0.759},"o":{"x":0.011,"y":0.227}},{"t":333.78,"s":[3.67],"i":{"x":0.722,"y":1},"o":{"x":0.35,"y":0.828}},{"t":355.74,"s":[0],"h":1},{"t":505.2,"s":[0],"h":1}]}},{"ty":7,"nm":"","v":{"a":0,"k":1}},{"ty":7,"nm":"","v":{"a":0,"k":0}}]}],"ip":0,"op":506.2,"st":0,"shapes":[{"ty":"gr","it":[{"ty":"rc","p":{"a":0,"k":[30,53.625]},"r":{"a":0,"k":0},"s":{"a":0,"k":[100,115]}},{"ty":"fl","c":{"a":0,"k":[0,0,0,0]},"o":{"a":0,"k":0}},{"ty":"tr","o":{"a":0,"k":100}}]},{"ty":"gr","it":[{"ty":"sh","ks":{"a":0,"k":{"c":true,"i":[[0,0],[0,0],[0,0],[0,0],[0,0],[0,0],[0,0],[0,0],[0,0]],"v":[[45,16.1],[45,31.1],[60,31.1],[60,91.1],[45,91.1],[45,31.1],[15,31.1],[15,16.1],[45,16.1]],"o":[[0,0],[0,0],[0,0],[0,0],[0,0],[0,0],[0,0],[0,0],[0,0]]}}},{"ty":"sh","ks":{"a":0,"k":{"c":true,"i":[[0,0],[0,0],[0,0],[0,0],[0,0]],"v":[[0,91.1],[0,31.1],[15,31.1],[15,91.1],[0,91.1]],"o":[[0,0],[0,0],[0,0],[0,0],[0,0]]}}},{"ty":"fl","c":{"a":0,"k":[0.153,0.137,0.024]},"o":{"a":0,"k":100}},{"ty":"tr","o":{"a":0,"k":100}}]}]},{"ind":62,"ty":3,"ks":{"p":{"a":0,"k":[20,4]}},"ip":0,"op":506.2,"st":0}]},{"id":"69","layers":[{"ind":68,"ty":4,"parent":67,"ks":{},"ef":[{"ty":29,"ef":[{"ty":0,"nm":"","v":{"a":1,"k":[{"t":0,"s":[33.33],"h":1},{"t":306.36,"s":[33.33],"i":{"x":0.174,"y":0.759},"o":{"x":0.011,"y":0.227}},{"t":328.32,"s":[3.67],"i":{"x":0.722,"y":1},"o":{"x":0.35,"y":0.828}},{"t":350.28,"s":[0],"h":1},{"t":505.2,"s":[0],"h":1}]}},{"ty":7,"nm":"","v":{"a":0,"k":1}},{"ty":7,"nm":"","v":{"a":0,"k":0}}]}],"ip":0,"op":506.2,"st":0,"shapes":[{"ty":"gr","it":[{"ty":"rc","p":{"a":0,"k":[7.5,53.625]},"r":{"a":0,"k":0},"s":{"a":0,"k":[55,115]}},{"ty":"fl","c":{"a":0,"k":[0,0,0,0]},"o":{"a":0,"k":0}},{"ty":"tr","o":{"a":0,"k":100}}]},{"ty":"gr","it":[{"ty":"sh","ks":{"a":0,"k":{"c":true,"i":[[0,0],[0,0],[0,0],[0,0],[0,0]],"v":[[0,91.1],[0,16.1],[15,16.1],[15,91.1],[0,91.1]],"o":[[0,0],[0,0],[0,0],[0,0],[0,0]]}}},{"ty":"fl","c":{"a":0,"k":[0.153,0.137,0.024]},"o":{"a":0,"k":100}},{"ty":"tr","o":{"a":0,"k":100}}]}]},{"ind":67,"ty":3,"ks":{"p":{"a":0,"k":[20,4]}},"ip":0,"op":506.2,"st":0}]},{"id":"74","layers":[{"ind":73,"ty":4,"parent":72,"ks":{},"ef":[{"ty":29,"ef":[{"ty":0,"nm":"","v":{"a":1,"k":[{"t":0,"s":[33.33],"h":1},{"t":300.9,"s":[33.33],"i":{"x":0.174,"y":0.759},"o":{"x":0.011,"y":0.227}},{"t":322.86,"s":[3.67],"i":{"x":0.722,"y":1},"o":{"x":0.35,"y":0.828}},{"t":344.82,"s":[0],"h":1},{"t":505.2,"s":[0],"h":1}]}},{"ty":7,"nm":"","v":{"a":0,"k":1}},{"ty":7,"nm":"","v":{"a":0,"k":0}}]}],"ip":0,"op":506.2,"st":0,"shapes":[{"ty":"gr","it":[{"ty":"rc","p":{"a":0,"k":[30,53.625]},"r":{"a":0,"k":0},"s":{"a":0,"k":[100,115]}},{"ty":"fl","c":{"a":0,"k":[0,0,0,0]},"o":{"a":0,"k":0}},{"ty":"tr","o":{"a":0,"k":100}}]},{"ty":"gr","it":[{"ty":"sh","ks":{"a":0,"k":{"c":true,"i":[[0,0],[0,0],[0,0],[0,0],[0,0],[0,0],[0,0],[0,0],[0,0],[0,0],[0,0],[0,0],[0,0]],"v":[[0,76.1],[0,31.1],[15,31.1],[15,76.1],[45,76.1],[45,61.1],[30,61.1],[30,46.1],[60,46.1],[60,91.1],[15,91.1],[15,76.1],[0,76.1]],"o":[[0,0],[0,0],[0,0],[0,0],[0,0],[0,0],[0,0],[0,0],[0,0],[0,0],[0,0],[0,0],[0,0]]}}},{"ty":"sh","ks":{"a":0,"k":{"c":true,"i":[[0,0],[0,0],[0,0],[0,0],[0,0]],"v":[[15,31.1],[15,16.1],[60,16.1],[60,31.1],[15,31.1]],"o":[[0,0],[0,0],[0,0],[0,0],[0,0]]}}},{"ty":"fl","c":{"a":0,"k":[0.153,0.137,0.024]},"o":{"a":0,"k":100}},{"ty":"tr","o":{"a":0,"k":100}}]}]},{"ind":72,"ty":3,"ks":{"p":{"a":0,"k":[20,4]}},"ip":0,"op":506.2,"st":0}]},{"id":"79","layers":[{"ind":78,"ty":4,"parent":77,"ks":{},"ef":[{"ty":29,"ef":[{"ty":0,"nm":"","v":{"a":1,"k":[{"t":0,"s":[33.33],"h":1},{"t":295.44,"s":[33.33],"i":{"x":0.174,"y":0.759},"o":{"x":0.011,"y":0.227}},{"t":317.4,"s":[3.67],"i":{"x":0.722,"y":1},"o":{"x":0.35,"y":0.828}},{"t":339.36,"s":[0],"h":1},{"t":505.2,"s":[0],"h":1}]}},{"ty":7,"nm":"","v":{"a":0,"k":1}},{"ty":7,"nm":"","v":{"a":0,"k":0}}]}],"ip":0,"op":506.2,"st":0,"shapes":[{"ty":"gr","it":[{"ty":"rc","p":{"a":0,"k":[30,53.625]},"r":{"a":0,"k":0},"s":{"a":0,"k":[100,115]}},{"ty":"fl","c":{"a":0,"k":[0,0,0,0]},"o":{"a":0,"k":0}},{"ty":"tr","o":{"a":0,"k":100}}]},{"ty":"gr","it":[{"ty":"sh","ks":{"a":0,"k":{"c":true,"i":[[0,0],[0,0],[0,0],[0,0],[0,0],[0,0],[0,0],[0,0],[0,0],[0,0],[0,0],[0,0],[0,0],[0,0],[0,0],[0,0],[0,0]],"v":[[0,91.1],[0,31.1],[15,31.1],[15,46.1],[45,46.1],[45,31.1],[15,31.1],[15,16.1],[45,16.1],[45,31.1],[60,31.1],[60,91.1],[45,91.1],[45,61.1],[15,61.1],[15,91.1],[0,91.1]],"o":[[0,0],[0,0],[0,0],[0,0],[0,0],[0,0],[0,0],[0,0],[0,0],[0,0],[0,0],[0,0],[0,0],[0,0],[0,0],[0,0],[0,0]]}}},{"ty":"fl","c":{"a":0,"k":[0.153,0.137,0.024]},"o":{"a":0,"k":100}},{"ty":"tr","o":{"a":0,"k":100}}]}]},{"ind":77,"ty":3,"ks":{"p":{"a":0,"k":[20,4]}},"ip":0,"op":506.2,"st":0}]},{"id":"84","layers":[{"ind":83,"ty":4,"parent":82,"ks":{},"ef":[{"ty":29,"ef":[{"ty":0,"nm":"","v":{"a":1,"k":[{"t":0,"s":[33.33],"h":1},{"t":289.98,"s":[33.33],"i":{"x":0.174,"y":0.759},"o":{"x":0.011,"y":0.227}},{"t":311.94,"s":[3.67],"i":{"x":0.722,"y":1},"o":{"x":0.35,"y":0.828}},{"t":333.9,"s":[0],"h":1},{"t":505.2,"s":[0],"h":1}]}},{"ty":7,"nm":"","v":{"a":0,"k":1}},{"ty":7,"nm":"","v":{"a":0,"k":0}}]}],"ip":0,"op":506.2,"st":0,"shapes":[{"ty":"gr","it":[{"ty":"rc","p":{"a":0,"k":[37.5,53.625]},"r":{"a":0,"k":0},"s":{"a":0,"k":[115,115]}},{"ty":"fl","c":{"a":0,"k":[0,0,0,0]},"o":{"a":0,"k":0}},{"ty":"tr","o":{"a":0,"k":100}}]},{"ty":"gr","it":[{"ty":"sh","ks":{"a":0,"k":{"c":true,"i":[[0,0],[0,0],[0,0],[0,0],[0,0]],"v":[[0,91.1],[0,31.1],[15,31.1],[15,91.1],[0,91.1]],"o":[[0,0],[0,0],[0,0],[0,0],[0,0]]}}},{"ty":"sh","ks":{"a":0,"k":{"c":true,"i":[[0,0],[0,0],[0,0],[0,0],[0,0]],"v":[[30,91.1],[30,31.1],[45,31.1],[45,91.1],[30,91.1]],"o":[[0,0],[0,0],[0,0],[0,0],[0,0]]}}},{"ty":"sh","ks":{"a":0,"k":{"c":true,"i":[[0,0],[0,0],[0,0],[0,0],[0,0]],"v":[[60,91.1],[60,31.1],[75,31.1],[75,91.1],[60,91.1]],"o":[[0,0],[0,0],[0,0],[0,0],[0,0]]}}},{"ty":"sh","ks":{"a":0,"k":{"c":true,"i":[[0,0],[0,0],[0,0],[0,0],[0,0]],"v":[[45,31.1],[45,16.1],[60,16.1],[60,31.1],[45,31.1]],"o":[[0,0],[0,0],[0,0],[0,0],[0,0]]}}},{"ty":"sh","ks":{"a":0,"k":{"c":true,"i":[[0,0],[0,0],[0,0],[0,0],[0,0]],"v":[[15,31.1],[15,16.1],[30,16.1],[30,31.1],[15,31.1]],"o":[[0,0],[0,0],[0,0],[0,0],[0,0]]}}},{"ty":"fl","c":{"a":0,"k":[0.153,0.137,0.024]},"o":{"a":0,"k":100}},{"ty":"tr","o":{"a":0,"k":100}}]}]},{"ind":82,"ty":3,"ks":{"p":{"a":0,"k":[20,4]}},"ip":0,"op":506.2,"st":0}]},{"id":"89","layers":[{"ind":88,"ty":4,"parent":87,"ks":{},"ef":[{"ty":29,"ef":[{"ty":0,"nm":"","v":{"a":1,"k":[{"t":0,"s":[33.33],"h":1},{"t":284.52,"s":[33.33],"i":{"x":0.174,"y":0.759},"o":{"x":0.011,"y":0.227}},{"t":306.48,"s":[3.67],"i":{"x":0.722,"y":1},"o":{"x":0.35,"y":0.828}},{"t":328.44,"s":[0],"h":1},{"t":505.2,"s":[0],"h":1}]}},{"ty":7,"nm":"","v":{"a":0,"k":1}},{"ty":7,"nm":"","v":{"a":0,"k":0}}]}],"ip":0,"op":506.2,"st":0,"shapes":[{"ty":"gr","it":[{"ty":"rc","p":{"a":0,"k":[7.5,53.625]},"r":{"a":0,"k":0},"s":{"a":0,"k":[55,115]}},{"ty":"fl","c":{"a":0,"k":[0,0,0,0]},"o":{"a":0,"k":0}},{"ty":"tr","o":{"a":0,"k":100}}]},{"ty":"gr","it":[{"ty":"sh","ks":{"a":0,"k":{"c":true,"i":[[0,0],[0,0],[0,0],[0,0],[0,0]],"v":[[0,91.1],[0,16.1],[15,16.1],[15,91.1],[0,91.1]],"o":[[0,0],[0,0],[0,0],[0,0],[0,0]]}}},{"ty":"fl","c":{"a":0,"k":[0.153,0.137,0.024]},"o":{"a":0,"k":100}},{"ty":"tr","o":{"a":0,"k":100}}]}]},{"ind":87,"ty":3,"ks":{"p":{"a":0,"k":[20,4]}},"ip":0,"op":506.2,"st":0}]},{"id":"94","layers":[{"ind":93,"ty":4,"parent":92,"ks":{},"ef":[{"ty":29,"ef":[{"ty":0,"nm":"","v":{"a":1,"k":[{"t":0,"s":[33.33],"h":1},{"t":279.06,"s":[33.33],"i":{"x":0.174,"y":0.759},"o":{"x":0.011,"y":0.227}},{"t":301.02,"s":[3.67],"i":{"x":0.722,"y":1},"o":{"x":0.35,"y":0.828}},{"t":322.98,"s":[0],"h":1},{"t":505.2,"s":[0],"h":1}]}},{"ty":7,"nm":"","v":{"a":0,"k":1}},{"ty":7,"nm":"","v":{"a":0,"k":0}}]}],"ip":0,"op":506.2,"st":0,"shapes":[{"ty":"gr","it":[{"ty":"rc","p":{"a":0,"k":[30,53.625]},"r":{"a":0,"k":0},"s":{"a":0,"k":[100,115]}},{"ty":"fl","c":{"a":0,"k":[0,0,0,0]},"o":{"a":0,"k":0}},{"ty":"tr","o":{"a":0,"k":100}}]},{"ty":"gr","it":[{"ty":"sh","ks":{"a":0,"k":{"c":true,"i":[[0,0],[0,0],[0,0],[0,0],[0,0],[0,0],[0,0],[0,0],[0,0]],"v":[[15,61.1],[15,76.1],[0,76.1],[0,31.1],[15,31.1],[15,46.1],[60,46.1],[60,61.1],[15,61.1]],"o":[[0,0],[0,0],[0,0],[0,0],[0,0],[0,0],[0,0],[0,0],[0,0]]}}},{"ty":"sh","ks":{"a":0,"k":{"c":true,"i":[[0,0],[0,0],[0,0],[0,0],[0,0]],"v":[[15,31.1],[15,16.1],[60,16.1],[60,31.1],[15,31.1]],"o":[[0,0],[0,0],[0,0],[0,0],[0,0]]}}},{"ty":"sh","ks":{"a":0,"k":{"c":true,"i":[[0,0],[0,0],[0,0],[0,0],[0,0]],"v":[[15,91.1],[15,76.1],[60,76.1],[60,91.1],[15,91.1]],"o":[[0,0],[0,0],[0,0],[0,0],[0,0]]}}},{"ty":"fl","c":{"a":0,"k":[0.153,0.137,0.024]},"o":{"a":0,"k":100}},{"ty":"tr","o":{"a":0,"k":100}}]}]},{"ind":92,"ty":3,"ks":{"p":{"a":0,"k":[20,4]}},"ip":0,"op":506.2,"st":0}]},{"id":"99","layers":[{"ind":98,"ty":4,"parent":97,"ks":{},"ef":[{"ty":29,"ef":[{"ty":0,"nm":"","v":{"a":1,"k":[{"t":0,"s":[33.33],"h":1},{"t":273.6,"s":[33.33],"i":{"x":0.174,"y":0.759},"o":{"x":0.011,"y":0.227}},{"t":295.56,"s":[3.67],"i":{"x":0.722,"y":1},"o":{"x":0.35,"y":0.828}},{"t":317.52,"s":[0],"h":1},{"t":505.2,"s":[0],"h":1}]}},{"ty":7,"nm":"","v":{"a":0,"k":1}},{"ty":7,"nm":"","v":{"a":0,"k":0}}]}],"ip":0,"op":506.2,"st":0,"shapes":[{"ty":"gr","it":[{"ty":"rc","p":{"a":0,"k":[30,53.625]},"r":{"a":0,"k":0},"s":{"a":0,"k":[100,115]}},{"ty":"fl","c":{"a":0,"k":[0,0,0,0]},"o":{"a":0,"k":0}},{"ty":"tr","o":{"a":0,"k":100}}]},{"ty":"gr","it":[{"ty":"sh","ks":{"a":0,"k":{"c":true,"i":[[0,0],[0,0],[0,0],[0,0],[0,0],[0,0],[0,0],[0,0],[0,0],[0,0],[0,0],[0,0],[0,0]],"v":[[15,31.1],[15,46.1],[45,46.1],[45,61.1],[60,61.1],[60,91.1],[45,91.1],[45,61.1],[15,61.1],[15,91.1],[0,91.1],[0,31.1],[15,31.1]],"o":[[0,0],[0,0],[0,0],[0,0],[0,0],[0,0],[0,0],[0,0],[0,0],[0,0],[0,0],[0,0],[0,0]]}}},{"ty":"sh","ks":{"a":0,"k":{"c":true,"i":[[0,0],[0,0],[0,0],[0,0],[0,0],[0,0],[0,0],[0,0],[0,0]],"v":[[45,16.1],[45,31.1],[60,31.1],[60,46.1],[45,46.1],[45,31.1],[15,31.1],[15,16.1],[45,16.1]],"o":[[0,0],[0,0],[0,0],[0,0],[0,0],[0,0],[0,0],[0,0],[0,0]]}}},{"ty":"fl","c":{"a":0,"k":[0.153,0.137,0.024]},"o":{"a":0,"k":100}},{"ty":"tr","o":{"a":0,"k":100}}]}]},{"ind":97,"ty":3,"ks":{"p":{"a":0,"k":[20,4]}},"ip":0,"op":506.2,"st":0}]},{"id":"102","layers":[{"ind":56,"ty":0,"parent":51,"ks":{"a":{"a":0,"k":[20,4]},"o":{"a":1,"k":[{"t":0,"s":[0],"h":1},{"t":322.74,"s":[0],"i":{"x":0,"y":1},"o":{"x":0,"y":0}},{"t":366.66,"s":[100],"h":1},{"t":505.2,"s":[100],"h":1}]},"p":{"a":0,"k":[735,0]}},"w":100,"h":116,"ip":0,"op":506.2,"st":0,"refId":"54"},{"ind":61,"ty":0,"parent":51,"ks":{"a":{"a":0,"k":[20,4]},"o":{"a":1,"k":[{"t":0,"s":[0],"h":1},{"t":317.28,"s":[0],"i":{"x":0,"y":1},"o":{"x":0,"y":0}},{"t":361.2,"s":[100],"h":1},{"t":505.2,"s":[100],"h":1}]},"p":{"a":0,"k":[645,0]}},"w":100,"h":116,"ip":0,"op":506.2,"st":0,"refId":"59"},{"ind":66,"ty":0,"parent":51,"ks":{"a":{"a":0,"k":[20,4]},"o":{"a":1,"k":[{"t":0,"s":[0],"h":1},{"t":311.82,"s":[0],"i":{"x":0,"y":1},"o":{"x":0,"y":0}},{"t":355.74,"s":[100],"h":1},{"t":505.2,"s":[100],"h":1}]},"p":{"a":0,"k":[555,0]}},"w":100,"h":116,"ip":0,"op":506.2,"st":0,"refId":"64"},{"ind":71,"ty":0,"parent":51,"ks":{"a":{"a":0,"k":[20,4]},"o":{"a":1,"k":[{"t":0,"s":[0],"h":1},{"t":306.36,"s":[0],"i":{"x":0,"y":1},"o":{"x":0,"y":0}},{"t":350.28,"s":[100],"h":1},{"t":505.2,"s":[100],"h":1}]},"p":{"a":0,"k":[510,0]}},"w":55,"h":116,"ip":0,"op":506.2,"st":0,"refId":"69"},{"ind":76,"ty":0,"parent":51,"ks":{"a":{"a":0,"k":[20,4]},"o":{"a":1,"k":[{"t":0,"s":[0],"h":1},{"t":300.9,"s":[0],"i":{"x":0,"y":1},"o":{"x":0,"y":0}},{"t":344.82,"s":[100],"h":1},{"t":505.2,"s":[100],"h":1}]},"p":{"a":0,"k":[420,0]}},"w":100,"h":116,"ip":0,"op":506.2,"st":0,"refId":"74"},{"ind":81,"ty":0,"parent":51,"ks":{"a":{"a":0,"k":[20,4]},"o":{"a":1,"k":[{"t":0,"s":[0],"h":1},{"t":295.44,"s":[0],"i":{"x":0,"y":1},"o":{"x":0,"y":0}},{"t":339.36,"s":[100],"h":1},{"t":505.2,"s":[100],"h":1}]},"p":{"a":0,"k":[330,0]}},"w":100,"h":116,"ip":0,"op":506.2,"st":0,"refId":"79"},{"ind":86,"ty":0,"parent":51,"ks":{"a":{"a":0,"k":[20,4]},"o":{"a":1,"k":[{"t":0,"s":[0],"h":1},{"t":289.98,"s":[0],"i":{"x":0,"y":1},"o":{"x":0,"y":0}},{"t":333.9,"s":[100],"h":1},{"t":505.2,"s":[100],"h":1}]},"p":{"a":0,"k":[225,0]}},"w":115,"h":116,"ip":0,"op":506.2,"st":0,"refId":"84"},{"ind":91,"ty":0,"parent":51,"ks":{"a":{"a":0,"k":[20,4]},"o":{"a":1,"k":[{"t":0,"s":[0],"h":1},{"t":284.52,"s":[0],"i":{"x":0,"y":1},"o":{"x":0,"y":0}},{"t":328.44,"s":[100],"h":1},{"t":505.2,"s":[100],"h":1}]},"p":{"a":0,"k":[180,0]}},"w":55,"h":116,"ip":0,"op":506.2,"st":0,"refId":"89"},{"ind":96,"ty":0,"parent":51,"ks":{"a":{"a":0,"k":[20,4]},"o":{"a":1,"k":[{"t":0,"s":[0],"h":1},{"t":279.06,"s":[0],"i":{"x":0,"y":1},"o":{"x":0,"y":0}},{"t":322.98,"s":[100],"h":1},{"t":505.2,"s":[100],"h":1}]},"p":{"a":0,"k":[90,0]}},"w":100,"h":116,"ip":0,"op":506.2,"st":0,"refId":"94"},{"ind":101,"ty":0,"parent":51,"ks":{"a":{"a":0,"k":[20,4]},"o":{"a":1,"k":[{"t":0,"s":[0],"h":1},{"t":273.6,"s":[0],"i":{"x":0,"y":1},"o":{"x":0,"y":0}},{"t":317.52,"s":[100],"h":1},{"t":505.2,"s":[100],"h":1}]}},"w":100,"h":116,"ip":0,"op":506.2,"st":0,"refId":"99"},{"ind":51,"ty":3,"ks":{"p":{"a":0,"k":[20,4]}},"ip":0,"op":506.2,"st":0}]},{"id":"106","layers":[{"ind":104,"ty":0,"ks":{"a":{"a":0,"k":[20,4]},"p":{"a":0,"k":[40,24]}},"w":835,"h":120,"ip":0,"op":506.2,"st":0,"refId":"102"},{"ind":105,"ty":4,"ks":{},"ip":0,"op":506.2,"st":0,"shapes":[{"ty":"rc","p":{"a":0,"k":[447.5,81.562]},"r":{"a":0,"k":0},"s":{"a":0,"k":[895,163.125]}},{"ty":"fl","c":{"a":0,"k":[0,0,0,0]},"o":{"a":0,"k":0}}]}]},{"id":"109","layers":[{"ind":108,"ty":0,"parent":50,"ks":{"p":{"a":0,"k":[-40,-24]}},"ef":[{"ty":29,"ef":[{"ty":0,"nm":"","v":{"a":1,"k":[{"t":0,"s":[0],"h":1},{"t":417.06,"s":[0],"i":{"x":0.65,"y":0.172},"o":{"x":0.278,"y":0}},{"t":435.06,"s":[3.67],"i":{"x":0.989,"y":0.773},"o":{"x":0.826,"y":0.241}},{"t":453.06,"s":[33.33],"h":1},{"t":505.2,"s":[33.33],"h":1}]}},{"ty":7,"nm":"","v":{"a":0,"k":1}},{"ty":7,"nm":"","v":{"a":0,"k":0}}]}],"w":895,"h":163.125,"ip":0,"op":506.2,"st":0,"refId":"106"},{"ind":50,"ty":3,"ks":{"p":{"a":0,"k":[40,24]}},"ip":0,"op":506.2,"st":0}]},{"id":"118","layers":[{"ind":117,"ty":4,"parent":116,"ks":{},"ef":[{"ty":29,"ef":[{"ty":0,"nm":"","v":{"a":1,"k":[{"t":0,"s":[33.33],"h":1},{"t":311.82,"s":[33.33],"i":{"x":0.174,"y":0.759},"o":{"x":0.011,"y":0.227}},{"t":333.78,"s":[3.67],"i":{"x":0.722,"y":1},"o":{"x":0.35,"y":0.828}},{"t":355.74,"s":[0],"h":1},{"t":505.2,"s":[0],"h":1}]}},{"ty":7,"nm":"","v":{"a":0,"k":1}},{"ty":7,"nm":"","v":{"a":0,"k":0}}]}],"ip":0,"op":506.2,"st":0,"shapes":[{"ty":"gr","it":[{"ty":"rc","p":{"a":0,"k":[30,53.625]},"r":{"a":0,"k":0},"s":{"a":0,"k":[100,115]}},{"ty":"fl","c":{"a":0,"k":[0,0,0,0]},"o":{"a":0,"k":0}},{"ty":"tr","o":{"a":0,"k":100}}]},{"ty":"gr","it":[{"ty":"sh","ks":{"a":0,"k":{"c":true,"i":[[0,0],[0,0],[0,0],[0,0],[0,0],[0,0],[0,0],[0,0],[0,0]],"v":[[45,16.1],[45,31.1],[60,31.1],[60,91.1],[45,91.1],[45,31.1],[15,31.1],[15,16.1],[45,16.1]],"o":[[0,0],[0,0],[0,0],[0,0],[0,0],[0,0],[0,0],[0,0],[0,0]]}}},{"ty":"sh","ks":{"a":0,"k":{"c":true,"i":[[0,0],[0,0],[0,0],[0,0],[0,0]],"v":[[0,91.1],[0,31.1],[15,31.1],[15,91.1],[0,91.1]],"o":[[0,0],[0,0],[0,0],[0,0],[0,0]]}}},{"ty":"fl","c":{"a":0,"k":[0.153,0.137,0.024]},"o":{"a":0,"k":100}},{"ty":"tr","o":{"a":0,"k":100}}]}]},{"ind":116,"ty":3,"ks":{"p":{"a":0,"k":[20,4]}},"ip":0,"op":506.2,"st":0}]},{"id":"123","layers":[{"ind":122,"ty":4,"parent":121,"ks":{},"ef":[{"ty":29,"ef":[{"ty":0,"nm":"","v":{"a":1,"k":[{"t":0,"s":[33.33],"h":1},{"t":306.36,"s":[33.33],"i":{"x":0.174,"y":0.759},"o":{"x":0.011,"y":0.227}},{"t":328.32,"s":[3.67],"i":{"x":0.722,"y":1},"o":{"x":0.35,"y":0.828}},{"t":350.28,"s":[0],"h":1},{"t":505.2,"s":[0],"h":1}]}},{"ty":7,"nm":"","v":{"a":0,"k":1}},{"ty":7,"nm":"","v":{"a":0,"k":0}}]}],"ip":0,"op":506.2,"st":0,"shapes":[{"ty":"gr","it":[{"ty":"rc","p":{"a":0,"k":[30,53.625]},"r":{"a":0,"k":0},"s":{"a":0,"k":[100,115]}},{"ty":"fl","c":{"a":0,"k":[0,0,0,0]},"o":{"a":0,"k":0}},{"ty":"tr","o":{"a":0,"k":100}}]},{"ty":"gr","it":[{"ty":"sh","ks":{"a":0,"k":{"c":true,"i":[[0,0],[0,0],[0,0],[0,0],[0,0],[0,0],[0,0],[0,0],[0,0]],"v":[[15,31.1],[15,76.1],[45,76.1],[45,91.1],[15,91.1],[15,76.1],[0,76.1],[0,31.1],[15,31.1]],"o":[[0,0],[0,0],[0,0],[0,0],[0,0],[0,0],[0,0],[0,0],[0,0]]}}},{"ty":"sh","ks":{"a":0,"k":{"c":true,"i":[[0,0],[0,0],[0,0],[0,0],[0,0]],"v":[[45,76.1],[45,31.1],[60,31.1],[60,76.1],[45,76.1]],"o":[[0,0],[0,0],[0,0],[0,0],[0,0]]}}},{"ty":"sh","ks":{"a":0,"k":{"c":true,"i":[[0,0],[0,0],[0,0],[0,0],[0,0]],"v":[[15,31.1],[15,16.1],[45,16.1],[45,31.1],[15,31.1]],"o":[[0,0],[0,0],[0,0],[0,0],[0,0]]}}},{"ty":"fl","c":{"a":0,"k":[0.153,0.137,0.024]},"o":{"a":0,"k":100}},{"ty":"tr","o":{"a":0,"k":100}}]}]},{"ind":121,"ty":3,"ks":{"p":{"a":0,"k":[20,4]}},"ip":0,"op":506.2,"st":0}]},{"id":"128","layers":[{"ind":127,"ty":4,"parent":126,"ks":{},"ef":[{"ty":29,"ef":[{"ty":0,"nm":"","v":{"a":1,"k":[{"t":0,"s":[33.33],"h":1},{"t":300.9,"s":[33.33],"i":{"x":0.174,"y":0.759},"o":{"x":0.011,"y":0.227}},{"t":322.86,"s":[3.67],"i":{"x":0.722,"y":1},"o":{"x":0.35,"y":0.828}},{"t":344.82,"s":[0],"h":1},{"t":505.2,"s":[0],"h":1}]}},{"ty":7,"nm":"","v":{"a":0,"k":1}},{"ty":7,"nm":"","v":{"a":0,"k":0}}]}],"ip":0,"op":506.2,"st":0,"shapes":[{"ty":"gr","it":[{"ty":"rc","p":{"a":0,"k":[7.5,53.625]},"r":{"a":0,"k":0},"s":{"a":0,"k":[55,115]}},{"ty":"fl","c":{"a":0,"k":[0,0,0,0]},"o":{"a":0,"k":0}},{"ty":"tr","o":{"a":0,"k":100}}]},{"ty":"gr","it":[{"ty":"sh","ks":{"a":0,"k":{"c":true,"i":[[0,0],[0,0],[0,0],[0,0],[0,0]],"v":[[0,91.1],[0,16.1],[15,16.1],[15,91.1],[0,91.1]],"o":[[0,0],[0,0],[0,0],[0,0],[0,0]]}}},{"ty":"fl","c":{"a":0,"k":[0.153,0.137,0.024]},"o":{"a":0,"k":100}},{"ty":"tr","o":{"a":0,"k":100}}]}]},{"ind":126,"ty":3,"ks":{"p":{"a":0,"k":[20,4]}},"ip":0,"op":506.2,"st":0}]},{"id":"133","layers":[{"ind":132,"ty":4,"parent":131,"ks":{},"ef":[{"ty":29,"ef":[{"ty":0,"nm":"","v":{"a":1,"k":[{"t":0,"s":[33.33],"h":1},{"t":295.44,"s":[33.33],"i":{"x":0.174,"y":0.759},"o":{"x":0.011,"y":0.227}},{"t":317.4,"s":[3.67],"i":{"x":0.722,"y":1},"o":{"x":0.35,"y":0.828}},{"t":339.36,"s":[0],"h":1},{"t":505.2,"s":[0],"h":1}]}},{"ty":7,"nm":"","v":{"a":0,"k":1}},{"ty":7,"nm":"","v":{"a":0,"k":0}}]}],"ip":0,"op":506.2,"st":0,"shapes":[{"ty":"gr","it":[{"ty":"rc","p":{"a":0,"k":[22.5,53.625]},"r":{"a":0,"k":0},"s":{"a":0,"k":[85,115]}},{"ty":"fl","c":{"a":0,"k":[0,0,0,0]},"o":{"a":0,"k":0}},{"ty":"tr","o":{"a":0,"k":100}}]},{"ty":"gr","it":[{"ty":"sh","ks":{"a":0,"k":{"c":true,"i":[[0,0],[0,0],[0,0],[0,0],[0,0],[0,0],[0,0],[0,0],[0,0]],"v":[[0,31.1],[0,16.1],[45,16.1],[45,31.1],[30,31.1],[30,91.1],[15,91.1],[15,31.1],[0,31.1]],"o":[[0,0],[0,0],[0,0],[0,0],[0,0],[0,0],[0,0],[0,0],[0,0]]}}},{"ty":"fl","c":{"a":0,"k":[0.153,0.137,0.024]},"o":{"a":0,"k":100}},{"ty":"tr","o":{"a":0,"k":100}}]}]},{"ind":131,"ty":3,"ks":{"p":{"a":0,"k":[20,4]}},"ip":0,"op":506.2,"st":0}]},{"id":"138","layers":[{"ind":137,"ty":4,"parent":136,"ks":{},"ef":[{"ty":29,"ef":[{"ty":0,"nm":"","v":{"a":1,"k":[{"t":0,"s":[33.33],"h":1},{"t":289.98,"s":[33.33],"i":{"x":0.174,"y":0.759},"o":{"x":0.011,"y":0.227}},{"t":311.94,"s":[3.67],"i":{"x":0.722,"y":1},"o":{"x":0.35,"y":0.828}},{"t":333.9,"s":[0],"h":1},{"t":505.2,"s":[0],"h":1}]}},{"ty":7,"nm":"","v":{"a":0,"k":1}},{"ty":7,"nm":"","v":{"a":0,"k":0}}]}],"ip":0,"op":506.2,"st":0,"shapes":[{"ty":"gr","it":[{"ty":"rc","p":{"a":0,"k":[30,53.625]},"r":{"a":0,"k":0},"s":{"a":0,"k":[100,115]}},{"ty":"fl","c":{"a":0,"k":[0,0,0,0]},"o":{"a":0,"k":0}},{"ty":"tr","o":{"a":0,"k":100}}]},{"ty":"gr","it":[{"ty":"sh","ks":{"a":0,"k":{"c":true,"i":[[0,0],[0,0],[0,0],[0,0],[0,0],[0,0],[0,0],[0,0],[0,0],[0,0],[0,0],[0,0],[0,0],[0,0],[0,0],[0,0],[0,0]],"v":[[0,91.1],[0,31.1],[15,31.1],[15,46.1],[45,46.1],[45,31.1],[15,31.1],[15,16.1],[45,16.1],[45,31.1],[60,31.1],[60,91.1],[45,91.1],[45,61.1],[15,61.1],[15,91.1],[0,91.1]],"o":[[0,0],[0,0],[0,0],[0,0],[0,0],[0,0],[0,0],[0,0],[0,0],[0,0],[0,0],[0,0],[0,0],[0,0],[0,0],[0,0],[0,0]]}}},{"ty":"fl","c":{"a":0,"k":[0.153,0.137,0.024]},"o":{"a":0,"k":100}},{"ty":"tr","o":{"a":0,"k":100}}]}]},{"ind":136,"ty":3,"ks":{"p":{"a":0,"k":[20,4]}},"ip":0,"op":506.2,"st":0}]},{"id":"143","layers":[{"ind":142,"ty":4,"parent":141,"ks":{},"ef":[{"ty":29,"ef":[{"ty":0,"nm":"","v":{"a":1,"k":[{"t":0,"s":[33.33],"h":1},{"t":284.52,"s":[33.33],"i":{"x":0.174,"y":0.759},"o":{"x":0.011,"y":0.227}},{"t":306.48,"s":[3.67],"i":{"x":0.722,"y":1},"o":{"x":0.35,"y":0.828}},{"t":328.44,"s":[0],"h":1},{"t":505.2,"s":[0],"h":1}]}},{"ty":7,"nm":"","v":{"a":0,"k":1}},{"ty":7,"nm":"","v":{"a":0,"k":0}}]}],"ip":0,"op":506.2,"st":0,"shapes":[{"ty":"gr","it":[{"ty":"rc","p":{"a":0,"k":[30,53.625]},"r":{"a":0,"k":0},"s":{"a":0,"k":[100,115]}},{"ty":"fl","c":{"a":0,"k":[0,0,0,0]},"o":{"a":0,"k":0}},{"ty":"tr","o":{"a":0,"k":100}}]},{"ty":"gr","it":[{"ty":"sh","ks":{"a":0,"k":{"c":true,"i":[[0,0],[0,0],[0,0],[0,0],[0,0],[0,0],[0,0],[0,0],[0,0]],"v":[[15,61.1],[15,76.1],[0,76.1],[0,31.1],[15,31.1],[15,46.1],[60,46.1],[60,61.1],[15,61.1]],"o":[[0,0],[0,0],[0,0],[0,0],[0,0],[0,0],[0,0],[0,0],[0,0]]}}},{"ty":"sh","ks":{"a":0,"k":{"c":true,"i":[[0,0],[0,0],[0,0],[0,0],[0,0]],"v":[[15,31.1],[15,16.1],[60,16.1],[60,31.1],[15,31.1]],"o":[[0,0],[0,0],[0,0],[0,0],[0,0]]}}},{"ty":"sh","ks":{"a":0,"k":{"c":true,"i":[[0,0],[0,0],[0,0],[0,0],[0,0]],"v":[[15,91.1],[15,76.1],[60,76.1],[60,91.1],[15,91.1]],"o":[[0,0],[0,0],[0,0],[0,0],[0,0]]}}},{"ty":"fl","c":{"a":0,"k":[0.153,0.137,0.024]},"o":{"a":0,"k":100}},{"ty":"tr","o":{"a":0,"k":100}}]}]},{"ind":141,"ty":3,"ks":{"p":{"a":0,"k":[20,4]}},"ip":0,"op":506.2,"st":0}]},{"id":"148","layers":[{"ind":147,"ty":4,"parent":146,"ks":{},"ef":[{"ty":29,"ef":[{"ty":0,"nm":"","v":{"a":1,"k":[{"t":0,"s":[33.33],"h":1},{"t":279.06,"s":[33.33],"i":{"x":0.174,"y":0.759},"o":{"x":0.011,"y":0.227}},{"t":301.02,"s":[3.67],"i":{"x":0.722,"y":1},"o":{"x":0.35,"y":0.828}},{"t":322.98,"s":[0],"h":1},{"t":505.2,"s":[0],"h":1}]}},{"ty":7,"nm":"","v":{"a":0,"k":1}},{"ty":7,"nm":"","v":{"a":0,"k":0}}]}],"ip":0,"op":506.2,"st":0,"shapes":[{"ty":"gr","it":[{"ty":"rc","p":{"a":0,"k":[30,53.625]},"r":{"a":0,"k":0},"s":{"a":0,"k":[100,115]}},{"ty":"fl","c":{"a":0,"k":[0,0,0,0]},"o":{"a":0,"k":0}},{"ty":"tr","o":{"a":0,"k":100}}]},{"ty":"gr","it":[{"ty":"sh","ks":{"a":0,"k":{"c":true,"i":[[0,0],[0,0],[0,0],[0,0],[0,0],[0,0],[0,0],[0,0],[0,0]],"v":[[45,16.1],[45,31.1],[15,31.1],[15,76.1],[45,76.1],[45,91.1],[0,91.1],[0,16.1],[45,16.1]],"o":[[0,0],[0,0],[0,0],[0,0],[0,0],[0,0],[0,0],[0,0],[0,0]]}}},{"ty":"sh","ks":{"a":0,"k":{"c":true,"i":[[0,0],[0,0],[0,0],[0,0],[0,0]],"v":[[45,76.1],[45,31.1],[60,31.1],[60,76.1],[45,76.1]],"o":[[0,0],[0,0],[0,0],[0,0],[0,0]]}}},{"ty":"fl","c":{"a":0,"k":[0.153,0.137,0.024]},"o":{"a":0,"k":100}},{"ty":"tr","o":{"a":0,"k":100}}]}]},{"ind":146,"ty":3,"ks":{"p":{"a":0,"k":[20,4]}},"ip":0,"op":506.2,"st":0}]},{"id":"153","layers":[{"ind":152,"ty":4,"parent":151,"ks":{},"ef":[{"ty":29,"ef":[{"ty":0,"nm":"","v":{"a":1,"k":[{"t":0,"s":[33.33],"h":1},{"t":273.6,"s":[33.33],"i":{"x":0.174,"y":0.759},"o":{"x":0.011,"y":0.227}},{"t":295.56,"s":[3.67],"i":{"x":0.722,"y":1},"o":{"x":0.35,"y":0.828}},{"t":317.52,"s":[0],"h":1},{"t":505.2,"s":[0],"h":1}]}},{"ty":7,"nm":"","v":{"a":0,"k":1}},{"ty":7,"nm":"","v":{"a":0,"k":0}}]}],"ip":0,"op":506.2,"st":0,"shapes":[{"ty":"gr","it":[{"ty":"rc","p":{"a":0,"k":[7.5,53.625]},"r":{"a":0,"k":0},"s":{"a":0,"k":[55,115]}},{"ty":"fl","c":{"a":0,"k":[0,0,0,0]},"o":{"a":0,"k":0}},{"ty":"tr","o":{"a":0,"k":100}}]},{"ty":"gr","it":[{"ty":"sh","ks":{"a":0,"k":{"c":true,"i":[[0,0],[0,0],[0,0],[0,0],[0,0]],"v":[[0,91.1],[0,16.1],[15,16.1],[15,91.1],[0,91.1]],"o":[[0,0],[0,0],[0,0],[0,0],[0,0]]}}},{"ty":"fl","c":{"a":0,"k":[0.153,0.137,0.024]},"o":{"a":0,"k":100}},{"ty":"tr","o":{"a":0,"k":100}}]}]},{"ind":151,"ty":3,"ks":{"p":{"a":0,"k":[20,4]}},"ip":0,"op":506.2,"st":0}]},{"id":"156","layers":[{"ind":120,"ty":0,"parent":115,"ks":{"a":{"a":0,"k":[20,4]},"o":{"a":1,"k":[{"t":0,"s":[0],"h":1},{"t":311.82,"s":[0],"i":{"x":0,"y":1},"o":{"x":0,"y":0}},{"t":355.74,"s":[100],"h":1},{"t":505.2,"s":[100],"h":1}]},"p":{"a":0,"k":[525,0]}},"w":100,"h":116,"ip":0,"op":506.2,"st":0,"refId":"118"},{"ind":125,"ty":0,"parent":115,"ks":{"a":{"a":0,"k":[20,4]},"o":{"a":1,"k":[{"t":0,"s":[0],"h":1},{"t":306.36,"s":[0],"i":{"x":0,"y":1},"o":{"x":0,"y":0}},{"t":350.28,"s":[100],"h":1},{"t":505.2,"s":[100],"h":1}]},"p":{"a":0,"k":[435,0]}},"w":100,"h":116,"ip":0,"op":506.2,"st":0,"refId":"123"},{"ind":130,"ty":0,"parent":115,"ks":{"a":{"a":0,"k":[20,4]},"o":{"a":1,"k":[{"t":0,"s":[0],"h":1},{"t":300.9,"s":[0],"i":{"x":0,"y":1},"o":{"x":0,"y":0}},{"t":344.82,"s":[100],"h":1},{"t":505.2,"s":[100],"h":1}]},"p":{"a":0,"k":[390,0]}},"w":55,"h":116,"ip":0,"op":506.2,"st":0,"refId":"128"},{"ind":135,"ty":0,"parent":115,"ks":{"a":{"a":0,"k":[20,4]},"o":{"a":1,"k":[{"t":0,"s":[0],"h":1},{"t":295.44,"s":[0],"i":{"x":0,"y":1},"o":{"x":0,"y":0}},{"t":339.36,"s":[100],"h":1},{"t":505.2,"s":[100],"h":1}]},"p":{"a":0,"k":[315,0]}},"w":85,"h":116,"ip":0,"op":506.2,"st":0,"refId":"133"},{"ind":140,"ty":0,"parent":115,"ks":{"a":{"a":0,"k":[20,4]},"o":{"a":1,"k":[{"t":0,"s":[0],"h":1},{"t":289.98,"s":[0],"i":{"x":0,"y":1},"o":{"x":0,"y":0}},{"t":333.9,"s":[100],"h":1},{"t":505.2,"s":[100],"h":1}]},"p":{"a":0,"k":[225,0]}},"w":100,"h":116,"ip":0,"op":506.2,"st":0,"refId":"138"},{"ind":145,"ty":0,"parent":115,"ks":{"a":{"a":0,"k":[20,4]},"o":{"a":1,"k":[{"t":0,"s":[0],"h":1},{"t":284.52,"s":[0],"i":{"x":0,"y":1},"o":{"x":0,"y":0}},{"t":328.44,"s":[100],"h":1},{"t":505.2,"s":[100],"h":1}]},"p":{"a":0,"k":[135,0]}},"w":100,"h":116,"ip":0,"op":506.2,"st":0,"refId":"143"},{"ind":150,"ty":0,"parent":115,"ks":{"a":{"a":0,"k":[20,4]},"o":{"a":1,"k":[{"t":0,"s":[0],"h":1},{"t":279.06,"s":[0],"i":{"x":0,"y":1},"o":{"x":0,"y":0}},{"t":322.98,"s":[100],"h":1},{"t":505.2,"s":[100],"h":1}]},"p":{"a":0,"k":[45,0]}},"w":100,"h":116,"ip":0,"op":506.2,"st":0,"refId":"148"},{"ind":155,"ty":0,"parent":115,"ks":{"a":{"a":0,"k":[20,4]},"o":{"a":1,"k":[{"t":0,"s":[0],"h":1},{"t":273.6,"s":[0],"i":{"x":0,"y":1},"o":{"x":0,"y":0}},{"t":317.52,"s":[100],"h":1},{"t":505.2,"s":[100],"h":1}]}},"w":55,"h":116,"ip":0,"op":506.2,"st":0,"refId":"153"},{"ind":115,"ty":3,"ks":{"p":{"a":0,"k":[20,4]}},"ip":0,"op":506.2,"st":0}]},{"id":"160","layers":[{"ind":158,"ty":0,"ks":{"a":{"a":0,"k":[20,4]},"p":{"a":0,"k":[40,24]}},"w":625,"h":120,"ip":0,"op":506.2,"st":0,"refId":"156"},{"ind":159,"ty":4,"ks":{},"ip":0,"op":506.2,"st":0,"shapes":[{"ty":"rc","p":{"a":0,"k":[342.5,81.562]},"r":{"a":0,"k":0},"s":{"a":0,"k":[685,163.125]}},{"ty":"fl","c":{"a":0,"k":[0,0,0,0]},"o":{"a":0,"k":0}}]}]},{"id":"163","layers":[{"ind":162,"ty":0,"parent":114,"ks":{"p":{"a":0,"k":[-40,-24]}},"ef":[{"ty":29,"ef":[{"ty":0,"nm":"","v":{"a":1,"k":[{"t":0,"s":[0],"h":1},{"t":417.06,"s":[0],"i":{"x":0.65,"y":0.172},"o":{"x":0.278,"y":0}},{"t":435.06,"s":[3.67],"i":{"x":0.989,"y":0.773},"o":{"x":0.826,"y":0.241}},{"t":453.06,"s":[33.33],"h":1},{"t":505.2,"s":[33.33],"h":1}]}},{"ty":7,"nm":"","v":{"a":0,"k":1}},{"ty":7,"nm":"","v":{"a":0,"k":0}}]}],"w":685,"h":163.125,"ip":0,"op":506.2,"st":0,"refId":"160"},{"ind":114,"ty":3,"ks":{"p":{"a":0,"k":[40,24]}},"ip":0,"op":506.2,"st":0}]},{"id":"171","layers":[{"ind":170,"ty":4,"parent":169,"ks":{},"ef":[{"ty":29,"ef":[{"ty":0,"nm":"","v":{"a":1,"k":[{"t":0,"s":[33.33],"h":1},{"t":46.8,"s":[33.33],"i":{"x":0.174,"y":0.759},"o":{"x":0.011,"y":0.227}},{"t":70.8,"s":[3.67],"i":{"x":0.722,"y":1},"o":{"x":0.35,"y":0.828}},{"t":94.8,"s":[0],"h":1},{"t":205.2,"s":[0],"i":{"x":0.65,"y":0.172},"o":{"x":0.278,"y":0}},{"t":223.2,"s":[3.67],"i":{"x":0.989,"y":0.773},"o":{"x":0.826,"y":0.241}},{"t":241.2,"s":[33.33],"h":1},{"t":505.2,"s":[33.33],"h":1}]}},{"ty":7,"nm":"","v":{"a":0,"k":1}},{"ty":7,"nm":"","v":{"a":0,"k":0}}]}],"ip":0,"op":506.2,"st":0,"shapes":[{"ty":"gr","it":[{"ty":"rc","p":{"a":0,"k":[44.6,79.722]},"r":{"a":0,"k":0},"s":{"a":0,"k":[129.2,151.5]}},{"ty":"fl","c":{"a":0,"k":[0,0,0,0]},"o":{"a":0,"k":0}},{"ty":"tr","o":{"a":0,"k":100}}]},{"ty":"gr","it":[{"ty":"sh","ks":{"a":0,"k":{"c":true,"i":[[0,0],[0,0],[0,0],[0,0],[0,0],[0,0],[0,0],[0,0],[0,0]],"v":[[22.3,90.9],[22.3,113.2],[0,113.2],[0,46.3],[22.3,46.3],[22.3,68.6],[89.2,68.6],[89.2,90.9],[22.3,90.9]],"o":[[0,0],[0,0],[0,0],[0,0],[0,0],[0,0],[0,0],[0,0],[0,0]]}}},{"ty":"sh","ks":{"a":0,"k":{"c":true,"i":[[0,0],[0,0],[0,0],[0,0],[0,0]],"v":[[22.3,46.3],[22.3,24],[89.2,24],[89.2,46.3],[22.3,46.3]],"o":[[0,0],[0,0],[0,0],[0,0],[0,0]]}}},{"ty":"sh","ks":{"a":0,"k":{"c":true,"i":[[0,0],[0,0],[0,0],[0,0],[0,0]],"v":[[22.3,135.5],[22.3,113.2],[89.2,113.2],[89.2,135.5],[22.3,135.5]],"o":[[0,0],[0,0],[0,0],[0,0],[0,0]]}}},{"ty":"fl","c":{"a":0,"k":[0.153,0.137,0.024]},"o":{"a":0,"k":100}},{"ty":"tr","o":{"a":0,"k":100}}]}]},{"ind":169,"ty":3,"ks":{"p":{"a":0,"k":[20,-3]}},"ip":0,"op":506.2,"st":0}]},{"id":"176","layers":[{"ind":175,"ty":4,"parent":174,"ks":{},"ef":[{"ty":29,"ef":[{"ty":0,"nm":"","v":{"a":1,"k":[{"t":0,"s":[33.33],"h":1},{"t":40.8,"s":[33.33],"i":{"x":0.174,"y":0.759},"o":{"x":0.011,"y":0.227}},{"t":64.8,"s":[3.67],"i":{"x":0.722,"y":1},"o":{"x":0.35,"y":0.828}},{"t":88.8,"s":[0],"h":1},{"t":199.8,"s":[0],"i":{"x":0.65,"y":0.172},"o":{"x":0.278,"y":0}},{"t":217.8,"s":[3.67],"i":{"x":0.989,"y":0.773},"o":{"x":0.826,"y":0.241}},{"t":235.8,"s":[33.33],"h":1},{"t":505.2,"s":[33.33],"h":1}]}},{"ty":7,"nm":"","v":{"a":0,"k":1}},{"ty":7,"nm":"","v":{"a":0,"k":0}}]}],"ip":0,"op":506.2,"st":0,"shapes":[{"ty":"gr","it":[{"ty":"rc","p":{"a":0,"k":[44.6,79.722]},"r":{"a":0,"k":0},"s":{"a":0,"k":[129.2,151.5]}},{"ty":"fl","c":{"a":0,"k":[0,0,0,0]},"o":{"a":0,"k":0}},{"ty":"tr","o":{"a":0,"k":100}}]},{"ty":"gr","it":[{"ty":"sh","ks":{"a":0,"k":{"c":true,"i":[[0,0],[0,0],[0,0],[0,0],[0,0]],"v":[[0,135.5],[0,113.2],[66.9,113.2],[66.9,135.5],[0,135.5]],"o":[[0,0],[0,0],[0,0],[0,0],[0,0]]}}},{"ty":"sh","ks":{"a":0,"k":{"c":true,"i":[[0,0],[0,0],[0,0],[0,0],[0,0]],"v":[[22.3,46.3],[22.3,24],[89.2,24],[89.2,46.3],[22.3,46.3]],"o":[[0,0],[0,0],[0,0],[0,0],[0,0]]}}},{"ty":"sh","ks":{"a":0,"k":{"c":true,"i":[[0,0],[0,0],[0,0],[0,0],[0,0],[0,0],[0,0],[0,0],[0,0]],"v":[[0,68.6],[0,46.3],[22.3,46.3],[22.3,68.6],[66.9,68.6],[66.9,90.9],[22.3,90.9],[22.3,68.6],[0,68.6]],"o":[[0,0],[0,0],[0,0],[0,0],[0,0],[0,0],[0,0],[0,0],[0,0]]}}},{"ty":"sh","ks":{"a":0,"k":{"c":true,"i":[[0,0],[0,0],[0,0],[0,0],[0,0]],"v":[[66.9,113.2],[66.9,90.9],[89.2,90.9],[89.2,113.2],[66.9,113.2]],"o":[[0,0],[0,0],[0,0],[0,0],[0,0]]}}},{"ty":"fl","c":{"a":0,"k":[0.153,0.137,0.024]},"o":{"a":0,"k":100}},{"ty":"tr","o":{"a":0,"k":100}}]}]},{"ind":174,"ty":3,"ks":{"p":{"a":0,"k":[20,-3]}},"ip":0,"op":506.2,"st":0}]},{"id":"181","layers":[{"ind":180,"ty":4,"parent":179,"ks":{},"ef":[{"ty":29,"ef":[{"ty":0,"nm":"","v":{"a":1,"k":[{"t":0,"s":[33.33],"h":1},{"t":34.8,"s":[33.33],"i":{"x":0.174,"y":0.759},"o":{"x":0.011,"y":0.227}},{"t":58.8,"s":[3.67],"i":{"x":0.722,"y":1},"o":{"x":0.35,"y":0.828}},{"t":82.8,"s":[0],"h":1},{"t":194.4,"s":[0],"i":{"x":0.65,"y":0.172},"o":{"x":0.278,"y":0}},{"t":212.4,"s":[3.67],"i":{"x":0.989,"y":0.773},"o":{"x":0.826,"y":0.241}},{"t":230.4,"s":[33.33],"h":1},{"t":505.2,"s":[33.33],"h":1}]}},{"ty":7,"nm":"","v":{"a":0,"k":1}},{"ty":7,"nm":"","v":{"a":0,"k":0}}]}],"ip":0,"op":506.2,"st":0,"shapes":[{"ty":"gr","it":[{"ty":"rc","p":{"a":0,"k":[44.6,79.722]},"r":{"a":0,"k":0},"s":{"a":0,"k":[129.2,151.5]}},{"ty":"fl","c":{"a":0,"k":[0,0,0,0]},"o":{"a":0,"k":0}},{"ty":"tr","o":{"a":0,"k":100}}]},{"ty":"gr","it":[{"ty":"sh","ks":{"a":0,"k":{"c":true,"i":[[0,0],[0,0],[0,0],[0,0],[0,0],[0,0],[0,0],[0,0],[0,0]],"v":[[22.3,46.3],[22.3,68.6],[66.9,68.6],[66.9,90.9],[22.3,90.9],[22.3,135.5],[0,135.5],[0,46.3],[22.3,46.3]],"o":[[0,0],[0,0],[0,0],[0,0],[0,0],[0,0],[0,0],[0,0],[0,0]]}}},{"ty":"sh","ks":{"a":0,"k":{"c":true,"i":[[0,0],[0,0],[0,0],[0,0],[0,0],[0,0],[0,0],[0,0],[0,0]],"v":[[66.9,24],[66.9,46.3],[89.2,46.3],[89.2,68.6],[66.9,68.6],[66.9,46.3],[22.3,46.3],[22.3,24],[66.9,24]],"o":[[0,0],[0,0],[0,0],[0,0],[0,0],[0,0],[0,0],[0,0],[0,0]]}}},{"ty":"fl","c":{"a":0,"k":[0.153,0.137,0.024]},"o":{"a":0,"k":100}},{"ty":"tr","o":{"a":0,"k":100}}]}]},{"ind":179,"ty":3,"ks":{"p":{"a":0,"k":[20,-3]}},"ip":0,"op":506.2,"st":0}]},{"id":"186","layers":[{"ind":185,"ty":4,"parent":184,"ks":{},"ef":[{"ty":29,"ef":[{"ty":0,"nm":"","v":{"a":1,"k":[{"t":0,"s":[33.33],"h":1},{"t":28.8,"s":[33.33],"i":{"x":0.174,"y":0.759},"o":{"x":0.011,"y":0.227}},{"t":52.8,"s":[3.67],"i":{"x":0.722,"y":1},"o":{"x":0.35,"y":0.828}},{"t":76.8,"s":[0],"h":1},{"t":189,"s":[0],"i":{"x":0.65,"y":0.172},"o":{"x":0.278,"y":0}},{"t":207,"s":[3.67],"i":{"x":0.989,"y":0.773},"o":{"x":0.826,"y":0.241}},{"t":225,"s":[33.33],"h":1},{"t":505.2,"s":[33.33],"h":1}]}},{"ty":7,"nm":"","v":{"a":0,"k":1}},{"ty":7,"nm":"","v":{"a":0,"k":0}}]}],"ip":0,"op":506.2,"st":0,"shapes":[{"ty":"gr","it":[{"ty":"rc","p":{"a":0,"k":[44.6,79.722]},"r":{"a":0,"k":0},"s":{"a":0,"k":[129.2,151.5]}},{"ty":"fl","c":{"a":0,"k":[0,0,0,0]},"o":{"a":0,"k":0}},{"ty":"tr","o":{"a":0,"k":100}}]},{"ty":"gr","it":[{"ty":"sh","ks":{"a":0,"k":{"c":true,"i":[[0,0],[0,0],[0,0],[0,0],[0,0],[0,0],[0,0],[0,0],[0,0],[0,0],[0,0],[0,0],[0,0],[0,0],[0,0],[0,0],[0,0]],"v":[[0,135.5],[0,46.3],[22.3,46.3],[22.3,68.6],[66.9,68.6],[66.9,46.3],[22.3,46.3],[22.3,24],[66.9,24],[66.9,46.3],[89.2,46.3],[89.2,135.5],[66.9,135.5],[66.9,90.9],[22.3,90.9],[22.3,135.5],[0,135.5]],"o":[[0,0],[0,0],[0,0],[0,0],[0,0],[0,0],[0,0],[0,0],[0,0],[0,0],[0,0],[0,0],[0,0],[0,0],[0,0],[0,0],[0,0]]}}},{"ty":"fl","c":{"a":0,"k":[0.153,0.137,0.024]},"o":{"a":0,"k":100}},{"ty":"tr","o":{"a":0,"k":100}}]}]},{"ind":184,"ty":3,"ks":{"p":{"a":0,"k":[20,-3]}},"ip":0,"op":506.2,"st":0}]},{"id":"191","layers":[{"ind":190,"ty":4,"parent":189,"ks":{},"ef":[{"ty":29,"ef":[{"ty":0,"nm":"","v":{"a":1,"k":[{"t":0,"s":[33.33],"h":1},{"t":22.8,"s":[33.33],"i":{"x":0.174,"y":0.759},"o":{"x":0.011,"y":0.227}},{"t":46.8,"s":[3.67],"i":{"x":0.722,"y":1},"o":{"x":0.35,"y":0.828}},{"t":70.8,"s":[0],"h":1},{"t":183.6,"s":[0],"i":{"x":0.65,"y":0.172},"o":{"x":0.278,"y":0}},{"t":201.6,"s":[3.67],"i":{"x":0.989,"y":0.773},"o":{"x":0.826,"y":0.241}},{"t":219.6,"s":[33.33],"h":1},{"t":505.2,"s":[33.33],"h":1}]}},{"ty":7,"nm":"","v":{"a":0,"k":1}},{"ty":7,"nm":"","v":{"a":0,"k":0}}]}],"ip":0,"op":506.2,"st":0,"shapes":[{"ty":"gr","it":[{"ty":"rc","p":{"a":0,"k":[44.6,79.722]},"r":{"a":0,"k":0},"s":{"a":0,"k":[129.2,151.5]}},{"ty":"fl","c":{"a":0,"k":[0,0,0,0]},"o":{"a":0,"k":0}},{"ty":"tr","o":{"a":0,"k":100}}]},{"ty":"gr","it":[{"ty":"sh","ks":{"a":0,"k":{"c":true,"i":[[0,0],[0,0],[0,0],[0,0],[0,0],[0,0],[0,0],[0,0],[0,0]],"v":[[66.9,24],[66.9,46.3],[89.2,46.3],[89.2,135.5],[66.9,135.5],[66.9,46.3],[22.3,46.3],[22.3,24],[66.9,24]],"o":[[0,0],[0,0],[0,0],[0,0],[0,0],[0,0],[0,0],[0,0],[0,0]]}}},{"ty":"sh","ks":{"a":0,"k":{"c":true,"i":[[0,0],[0,0],[0,0],[0,0],[0,0]],"v":[[0,135.5],[0,46.3],[22.3,46.3],[22.3,135.5],[0,135.5]],"o":[[0,0],[0,0],[0,0],[0,0],[0,0]]}}},{"ty":"fl","c":{"a":0,"k":[0.153,0.137,0.024]},"o":{"a":0,"k":100}},{"ty":"tr","o":{"a":0,"k":100}}]}]},{"ind":189,"ty":3,"ks":{"p":{"a":0,"k":[20,-3]}},"ip":0,"op":506.2,"st":0}]},{"id":"196","layers":[{"ind":195,"ty":4,"parent":194,"ks":{},"ef":[{"ty":29,"ef":[{"ty":0,"nm":"","v":{"a":1,"k":[{"t":0,"s":[33.33],"h":1},{"t":16.8,"s":[33.33],"i":{"x":0.174,"y":0.759},"o":{"x":0.011,"y":0.227}},{"t":40.8,"s":[3.67],"i":{"x":0.722,"y":1},"o":{"x":0.35,"y":0.828}},{"t":64.8,"s":[0],"h":1},{"t":178.2,"s":[0],"i":{"x":0.65,"y":0.172},"o":{"x":0.278,"y":0}},{"t":196.2,"s":[3.67],"i":{"x":0.989,"y":0.773},"o":{"x":0.826,"y":0.241}},{"t":214.2,"s":[33.33],"h":1},{"t":505.2,"s":[33.33],"h":1}]}},{"ty":7,"nm":"","v":{"a":0,"k":1}},{"ty":7,"nm":"","v":{"a":0,"k":0}}]}],"ip":0,"op":506.2,"st":0,"shapes":[{"ty":"gr","it":[{"ty":"rc","p":{"a":0,"k":[44.6,79.722]},"r":{"a":0,"k":0},"s":{"a":0,"k":[129.2,151.5]}},{"ty":"fl","c":{"a":0,"k":[0,0,0,0]},"o":{"a":0,"k":0}},{"ty":"tr","o":{"a":0,"k":100}}]},{"ty":"gr","it":[{"ty":"sh","ks":{"a":0,"k":{"c":true,"i":[[0,0],[0,0],[0,0],[0,0],[0,0],[0,0],[0,0],[0,0],[0,0],[0,0],[0,0],[0,0],[0,0]],"v":[[0,68.6],[0,24],[22.3,24],[22.3,68.6],[66.9,68.6],[66.9,24],[89.2,24],[89.2,113.2],[66.9,113.2],[66.9,90.9],[22.3,90.9],[22.3,68.6],[0,68.6]],"o":[[0,0],[0,0],[0,0],[0,0],[0,0],[0,0],[0,0],[0,0],[0,0],[0,0],[0,0],[0,0],[0,0]]}}},{"ty":"sh","ks":{"a":0,"k":{"c":true,"i":[[0,0],[0,0],[0,0],[0,0],[0,0]],"v":[[0,135.5],[0,113.2],[66.9,113.2],[66.9,135.5],[0,135.5]],"o":[[0,0],[0,0],[0,0],[0,0],[0,0]]}}},{"ty":"fl","c":{"a":0,"k":[0.153,0.137,0.024]},"o":{"a":0,"k":100}},{"ty":"tr","o":{"a":0,"k":100}}]}]},{"ind":194,"ty":3,"ks":{"p":{"a":0,"k":[20,-3]}},"ip":0,"op":506.2,"st":0}]},{"id":"201","layers":[{"ind":200,"ty":4,"parent":199,"ks":{},"ef":[{"ty":29,"ef":[{"ty":0,"nm":"","v":{"a":1,"k":[{"t":0,"s":[33.33],"h":1},{"t":10.8,"s":[33.33],"i":{"x":0.174,"y":0.759},"o":{"x":0.011,"y":0.227}},{"t":34.8,"s":[3.67],"i":{"x":0.722,"y":1},"o":{"x":0.35,"y":0.828}},{"t":58.8,"s":[0],"h":1},{"t":172.8,"s":[0],"i":{"x":0.65,"y":0.172},"o":{"x":0.278,"y":0}},{"t":190.8,"s":[3.67],"i":{"x":0.989,"y":0.773},"o":{"x":0.826,"y":0.241}},{"t":208.8,"s":[33.33],"h":1},{"t":505.2,"s":[33.33],"h":1}]}},{"ty":7,"nm":"","v":{"a":0,"k":1}},{"ty":7,"nm":"","v":{"a":0,"k":0}}]}],"ip":0,"op":506.2,"st":0,"shapes":[{"ty":"gr","it":[{"ty":"rc","p":{"a":0,"k":[44.6,79.722]},"r":{"a":0,"k":0},"s":{"a":0,"k":[129.2,151.5]}},{"ty":"fl","c":{"a":0,"k":[0,0,0,0]},"o":{"a":0,"k":0}},{"ty":"tr","o":{"a":0,"k":100}}]},{"ty":"gr","it":[{"ty":"sh","ks":{"a":0,"k":{"c":true,"i":[[0,0],[0,0],[0,0],[0,0],[0,0]],"v":[[0,135.5],[0,113.2],[66.9,113.2],[66.9,135.5],[0,135.5]],"o":[[0,0],[0,0],[0,0],[0,0],[0,0]]}}},{"ty":"sh","ks":{"a":0,"k":{"c":true,"i":[[0,0],[0,0],[0,0],[0,0],[0,0]],"v":[[22.3,46.3],[22.3,24],[89.2,24],[89.2,46.3],[22.3,46.3]],"o":[[0,0],[0,0],[0,0],[0,0],[0,0]]}}},{"ty":"sh","ks":{"a":0,"k":{"c":true,"i":[[0,0],[0,0],[0,0],[0,0],[0,0],[0,0],[0,0],[0,0],[0,0]],"v":[[0,68.6],[0,46.3],[22.3,46.3],[22.3,68.6],[66.9,68.6],[66.9,90.9],[22.3,90.9],[22.3,68.6],[0,68.6]],"o":[[0,0],[0,0],[0,0],[0,0],[0,0],[0,0],[0,0],[0,0],[0,0]]}}},{"ty":"sh","ks":{"a":0,"k":{"c":true,"i":[[0,0],[0,0],[0,0],[0,0],[0,0]],"v":[[66.9,113.2],[66.9,90.9],[89.2,90.9],[89.2,113.2],[66.9,113.2]],"o":[[0,0],[0,0],[0,0],[0,0],[0,0]]}}},{"ty":"fl","c":{"a":0,"k":[0.153,0.137,0.024]},"o":{"a":0,"k":100}},{"ty":"tr","o":{"a":0,"k":100}}]}]},{"ind":199,"ty":3,"ks":{"p":{"a":0,"k":[20,-3]}},"ip":0,"op":506.2,"st":0}]}],"fr":60,"h":1096,"ip":0,"layers":[{"ind":22,"ty":0,"parent":2,"ks":{"a":{"a":0,"k":[130,40]},"o":{"a":1,"k":[{"t":0,"s":[100],"h":1},{"t":178.2,"s":[100],"i":{"x":1,"y":1},"o":{"x":1,"y":0}},{"t":226.2,"s":[0],"h":1},{"t":505.2,"s":[0],"h":1}]}},"w":370,"h":341,"ip":0,"op":506.2,"st":0,"refId":"20"},{"ind":2,"ty":3,"parent":1,"ks":{"p":{"a":0,"k":[359,396]}},"ip":0,"op":506.2,"st":0},{"ind":47,"ty":0,"parent":23,"ks":{"a":{"a":0,"k":[95,40]},"o":{"a":1,"k":[{"t":0,"s":[100],"h":1},{"t":181.2,"s":[100],"i":{"x":1,"y":1},"o":{"x":1,"y":0}},{"t":229.2,"s":[0],"h":1},{"t":505.2,"s":[0],"h":1}]}},"w":265,"h":221,"ip":0,"op":506.2,"st":0,"refId":"45"},{"ind":23,"ty":3,"parent":1,"ks":{"p":{"a":0,"k":[359,386]}},"ip":0,"op":506.2,"st":0},{"ind":111,"ty":0,"parent":49,"ks":{"a":{"a":0,"k":[40,24]},"o":{"a":1,"k":[{"t":0,"s":[100],"h":1},{"t":417.06,"s":[100],"i":{"x":1,"y":1},"o":{"x":1,"y":0}},{"t":453.06,"s":[0],"h":1},{"t":505.2,"s":[0],"h":1}]}},"w":895,"h":164,"ip":0,"op":506.2,"st":0,"refId":"109"},{"ind":49,"ty":3,"parent":48,"ks":{"p":{"a":0,"k":[-43,0]}},"ip":0,"op":506.2,"st":0},{"ind":48,"ty":3,"parent":1,"ks":{"p":{"a":0,"k":[603,543]}},"ip":0,"op":506.2,"st":0},{"ind":165,"ty":0,"parent":113,"ks":{"a":{"a":0,"k":[40,24]},"o":{"a":1,"k":[{"t":0,"s":[100],"h":1},{"t":417.06,"s":[100],"i":{"x":1,"y":1},"o":{"x":1,"y":0}},{"t":453.06,"s":[0],"h":1},{"t":505.2,"s":[0],"h":1}]}},"w":685,"h":164,"ip":0,"op":506.2,"st":0,"refId":"163"},{"ind":113,"ty":3,"parent":112,"ks":{"p":{"a":0,"k":[62,0]}},"ip":0,"op":506.2,"st":0},{"ind":112,"ty":3,"parent":1,"ks":{"p":{"a":0,"k":[598,415]}},"ip":0,"op":506.2,"st":0},{"ind":173,"ty":0,"parent":168,"ks":{"a":{"a":0,"k":[20,-3]},"o":{"a":1,"k":[{"t":0,"s":[0],"h":1},{"t":46.8,"s":[0],"i":{"x":0,"y":1},"o":{"x":0,"y":0}},{"t":94.8,"s":[100],"h":1},{"t":205.2,"s":[100],"i":{"x":1,"y":1},"o":{"x":1,"y":0}},{"t":241.2,"s":[0],"h":1},{"t":505.2,"s":[0],"h":1}]},"p":{"a":0,"k":[805.8,0]}},"w":130,"h":153,"ip":0,"op":506.2,"st":0,"refId":"171"},{"ind":178,"ty":0,"parent":168,"ks":{"a":{"a":0,"k":[20,-3]},"o":{"a":1,"k":[{"t":0,"s":[0],"h":1},{"t":40.8,"s":[0],"i":{"x":0,"y":1},"o":{"x":0,"y":0}},{"t":88.8,"s":[100],"h":1},{"t":199.8,"s":[100],"i":{"x":1,"y":1},"o":{"x":1,"y":0}},{"t":235.8,"s":[0],"h":1},{"t":505.2,"s":[0],"h":1}]},"p":{"a":0,"k":[671.5,0]}},"w":130,"h":153,"ip":0,"op":506.2,"st":0,"refId":"176"},{"ind":183,"ty":0,"parent":168,"ks":{"a":{"a":0,"k":[20,-3]},"o":{"a":1,"k":[{"t":0,"s":[0],"h":1},{"t":34.8,"s":[0],"i":{"x":0,"y":1},"o":{"x":0,"y":0}},{"t":82.8,"s":[100],"h":1},{"t":194.4,"s":[100],"i":{"x":1,"y":1},"o":{"x":1,"y":0}},{"t":230.4,"s":[0],"h":1},{"t":505.2,"s":[0],"h":1}]},"p":{"a":0,"k":[537.2,0]}},"w":130,"h":153,"ip":0,"op":506.2,"st":0,"refId":"181"},{"ind":188,"ty":0,"parent":168,"ks":{"a":{"a":0,"k":[20,-3]},"o":{"a":1,"k":[{"t":0,"s":[0],"h":1},{"t":28.8,"s":[0],"i":{"x":0,"y":1},"o":{"x":0,"y":0}},{"t":76.8,"s":[100],"h":1},{"t":189,"s":[100],"i":{"x":1,"y":1},"o":{"x":1,"y":0}},{"t":225,"s":[0],"h":1},{"t":505.2,"s":[0],"h":1}]},"p":{"a":0,"k":[402.9,0]}},"w":130,"h":153,"ip":0,"op":506.2,"st":0,"refId":"186"},{"ind":193,"ty":0,"parent":168,"ks":{"a":{"a":0,"k":[20,-3]},"o":{"a":1,"k":[{"t":0,"s":[0],"h":1},{"t":22.8,"s":[0],"i":{"x":0,"y":1},"o":{"x":0,"y":0}},{"t":70.8,"s":[100],"h":1},{"t":183.6,"s":[100],"i":{"x":1,"y":1},"o":{"x":1,"y":0}},{"t":219.6,"s":[0],"h":1},{"t":505.2,"s":[0],"h":1}]},"p":{"a":0,"k":[268.6,0]}},"w":130,"h":153,"ip":0,"op":506.2,"st":0,"refId":"191"},{"ind":198,"ty":0,"parent":168,"ks":{"a":{"a":0,"k":[20,-3]},"o":{"a":1,"k":[{"t":0,"s":[0],"h":1},{"t":16.8,"s":[0],"i":{"x":0,"y":1},"o":{"x":0,"y":0}},{"t":64.8,"s":[100],"h":1},{"t":178.2,"s":[100],"i":{"x":1,"y":1},"o":{"x":1,"y":0}},{"t":214.2,"s":[0],"h":1},{"t":505.2,"s":[0],"h":1}]},"p":{"a":0,"k":[134.3,0]}},"w":130,"h":153,"ip":0,"op":506.2,"st":0,"refId":"196"},{"ind":203,"ty":0,"parent":168,"ks":{"a":{"a":0,"k":[20,-3]},"o":{"a":1,"k":[{"t":0,"s":[0],"h":1},{"t":10.8,"s":[0],"i":{"x":0,"y":1},"o":{"x":0,"y":0}},{"t":58.8,"s":[100],"h":1},{"t":172.8,"s":[100],"i":{"x":1,"y":1},"o":{"x":1,"y":0}},{"t":208.8,"s":[0],"h":1},{"t":505.2,"s":[0],"h":1}]}},"w":130,"h":153,"ip":0,"op":506.2,"st":0,"refId":"201"},{"ind":168,"ty":3,"parent":167,"ks":{},"ip":0,"op":506.2,"st":0},{"ind":167,"ty":3,"parent":166,"ks":{},"ip":0,"op":506.2,"st":0},{"ind":166,"ty":3,"parent":1,"ks":{"p":{"a":0,"k":[595,431]}},"ip":0,"op":506.2,"st":0},{"ind":1,"ty":3,"parent":0,"ks":{},"ip":0,"op":506.2,"st":0},{"ind":204,"ty":4,"parent":0,"ks":{},"ip":0,"op":506.2,"st":0,"shapes":[{"ty":"rc","p":{"a":0,"k":[970,548]},"r":{"a":0,"k":0},"s":{"a":0,"k":[1940,1096]}},{"ty":"fl","c":{"a":0,"k":[0.773,0.875,0]},"o":{"a":0,"k":100}}]},{"ind":0,"ty":3,"ks":{},"ip":0,"op":506.2,"st":0}],"meta":{"g":"https://jitter.video"},"op":505.2,"v":"5.7.4","w":1940}